[{"username":"selvia","email":"silvianagy69@gmail.com","password":"w3e45t67y8uijh","confirmpassword":"w3e45t67y8uijh","hereyouhere":"facebook"},{"username":"asdfg","email":"ahmed@gmail.com","password":"etwyrfkg","confirmpassword":"etwyrfkg","hereyouhere":"facebook"},{"username":"ertyui","email":"nada@gmail.com","password":"ryjhiuk","confirmpassword":"ryjhiuk","hereyouhere":"twitter "},{"username":"SelviaNagy","email":"mahmod@gmail.com","password":"M.1234","confirmpassword":"M.1234","hereyouhere":"facebook"},{"username":"nada","email":"nagy@gmail.com","password":"Nada.1234","confirmpassword":"Nada.1234","hereyouhere":"twitter "},{"username":"ertyui","email":"ssss.56@gmail.com","password":"12345678uytfd","confirmpassword":"12345678uytfd","hereyouhere":"google"},{"username":"selvia","email":"fffff@gmail.com","password":"23456788uytgfdxcvn","confirmpassword":"23456788uytgfdxcvn","hereyouhere":"google"}]